grafmon/__init__.py
grafmon/app.py
grafmon/context.py
grafmon/dialogs.py
grafmon/filemonitor.py
grafmon/hoverablecurveitem.py
grafmon/mainwindow.py
grafmon/monitor.py
grafmon/timer.py
grafmon/monitors/avgpcpu
grafmon/monitors/cuc
grafmon/monitors/cuu
grafmon/monitors/drs
grafmon/monitors/pcpu
grafmon/monitors/pmem
grafmon/monitors/pss
grafmon/monitors/rbytes
grafmon/monitors/rchars
grafmon/monitors/rops
grafmon/monitors/rss
grafmon/monitors/sz
grafmon/monitors/thcount
grafmon/monitors/trs
grafmon/monitors/vsz
grafmon/monitors/wbytes
grafmon/monitors/wcbytes
grafmon/monitors/wchars
grafmon/monitors/wops
grafmon-1.1.1.dist-info/LICENSE
grafmon-1.1.1.dist-info/METADATA
grafmon-1.1.1.dist-info/WHEEL
grafmon-1.1.1.dist-info/entry_points.txt
grafmon-1.1.1.dist-info/top_level.txt
grafmon-1.1.1.dist-info/RECORD
