Metadata-Version: 2.1
Name: grafmon
Version: 1.1.1
Summary: Monitor metrics in a real-time time-series line-graph (a-la perfmon.exe)
Author-email: Pragmatic Software <pragma78@gmail.com>
License: Copyright (c) 2024-2025 Pragmatic Software <pragma78@gmail.com>
Project-URL: Homepage, https://github.com/pragma-/grafmon
Project-URL: Repository, https://github.com/pragma-/grafmon.git
Project-URL: Issues, https://github.com/pragma-/grafmon/issues
Keywords: graph,perfmon,perfmon.exe,pyqtgraph,metrics,monitor,perf,performance,cpu,pcpu,rss,process,memory,ram
Classifier: Development Status :: 5 - Production/Stable
Classifier: Programming Language :: Python :: 3
Classifier: Environment :: X11 Applications
Classifier: Environment :: X11 Applications :: Qt
Classifier: Intended Audience :: Developers
Classifier: Intended Audience :: End Users/Desktop
Classifier: Intended Audience :: Information Technology
Classifier: Intended Audience :: System Administrators
Classifier: License :: OSI Approved :: MIT License
Classifier: Operating System :: POSIX
Classifier: Topic :: System :: Monitoring
Classifier: Topic :: Utilities
Requires-Python: >=3.7
License-File: LICENSE
Requires-Dist: pyqtgraph
Requires-Dist: PyQt6
Requires-Dist: psutil
